hb_organiser/__init__.py
hb_organiser/bundle_objects.py
hb_organiser/check.py
hb_organiser/cli.py
hb_organiser/config.py
hb_organiser/logger.py
hb_organiser/organiser.py
tests/__init__.py
tests/test_checks.py
tests/test_cli.py
hb_organiser-1.0.9.dist-info/LICENSE
hb_organiser-1.0.9.dist-info/METADATA
hb_organiser-1.0.9.dist-info/WHEEL
hb_organiser-1.0.9.dist-info/entry_points.txt
hb_organiser-1.0.9.dist-info/top_level.txt
hb_organiser-1.0.9.dist-info/RECORD
