Metadata-Version: 2.1
Name: hb-organiser
Version: 1.0.9
Summary: Organises Humble Bundle bundles based on their platform.
Home-page: https://github.com/WhaleJ84/hb_organiser
Author: James Whale
Author-email: james@james-whale.com
License: UNKNOWN
Platform: UNKNOWN
Classifier: Programming Language :: Python :: 3.6
Classifier: Programming Language :: Python :: 3.7
Classifier: Programming Language :: Python :: 3.8
Classifier: Programming Language :: Python :: 3.9
Classifier: License :: OSI Approved :: MIT License
Classifier: Operating System :: POSIX :: Linux
Classifier: Natural Language :: English
Requires-Python: >=3.6
